[
  {"word":"abandon","pos":["v"],"level":["TOEIC"],"meaningKo":"버리다"},
  {"word":"ability","pos":["n"],"level":["TOEIC"],"meaningKo":"능력"},
  {"word":"able","pos":["adj"],"level":["TOEIC"],"meaningKo":"할 수 있는"},
  {"word":"about","pos":["prep","adv"],"level":["TOEIC"],"meaningKo":"~에 대해"},
  {"word":"above","pos":["prep","adv"],"level":["TOEIC"],"meaningKo":"위에"},
  {"word":"abroad","pos":["adv"],"level":["TOEIC"],"meaningKo":"해외에"},
  {"word":"absence","pos":["n"],"level":["TOEIC"],"meaningKo":"부재"},
  {"word":"accept","pos":["v"],"level":["TOEIC"],"meaningKo":"수락하다"},
  {"word":"access","pos":["n","v"],"level":["TOEIC"],"meaningKo":"접근"},
  {"word":"accident","pos":["n"],"level":["TOEIC"],"meaningKo":"사고"},
  {"word":"accommodate","pos":["v"],"level":["TOEIC"],"meaningKo":"수용하다"},
  {"word":"accomplish","pos":["v"],"level":["TOEIC"],"meaningKo":"성취하다"},
  {"word":"according","pos":["adv"],"level":["TOEIC"],"meaningKo":"~에 따르면"},
  {"word":"account","pos":["n","v"],"level":["TOEIC"],"meaningKo":"계좌; 설명하다"},
  {"word":"accurate","pos":["adj"],"level":["TOEIC"],"meaningKo":"정확한"},
  {"word":"achieve","pos":["v"],"level":["TOEIC"],"meaningKo":"달성하다"},
  {"word":"acknowledge","pos":["v"],"level":["TOEIC"],"meaningKo":"인정하다"},
  {"word":"acquire","pos":["v"],"level":["TOEIC"],"meaningKo":"획득하다"},
  {"word":"actual","pos":["adj"],"level":["TOEIC"],"meaningKo":"실제의"},
  {"word":"additional","pos":["adj"],"level":["TOEIC"],"meaningKo":"추가의"},
  {"word":"address","pos":["n","v"],"level":["TOEIC"],"meaningKo":"주소; 다루다"},
  {"word":"adequate","pos":["adj"],"level":["TOEIC"],"meaningKo":"적절한"},
  {"word":"adjust","pos":["v"],"level":["TOEIC"],"meaningKo":"조정하다"},
  {"word":"administration","pos":["n"],"level":["TOEIC"],"meaningKo":"관리; 행정"},
  {"word":"admission","pos":["n"],"level":["TOEIC"],"meaningKo":"입장; 입학"},
  {"word":"advance","pos":["n","v"],"level":["TOEIC"],"meaningKo":"진보; 전진하다"},
  {"word":"advantage","pos":["n"],"level":["TOEIC"],"meaningKo":"이점"},
  {"word":"advertise","pos":["v"],"level":["TOEIC"],"meaningKo":"광고하다"},
  {"word":"advice","pos":["n"],"level":["TOEIC"],"meaningKo":"조언"},
  {"word":"afford","pos":["v"],"level":["TOEIC"],"meaningKo":"~할 여유가 있다"},
  {"word":"agenda","pos":["n"],"level":["TOEIC"],"meaningKo":"안건; 의제"},
  {"word":"agree","pos":["v"],"level":["TOEIC"],"meaningKo":"동의하다"},
  {"word":"agreement","pos":["n"],"level":["TOEIC"],"meaningKo":"합의; 계약"},
  {"word":"allocate","pos":["v"],"level":["TOEIC"],"meaningKo":"할당하다"},
  {"word":"allow","pos":["v"],"level":["TOEIC"],"meaningKo":"허용하다"},
  {"word":"alternative","pos":["n","adj"],"level":["TOEIC"],"meaningKo":"대안; 대체의"},
  {"word":"amount","pos":["n"],"level":["TOEIC"],"meaningKo":"양; 금액"},
  {"word":"analyze","pos":["v"],"level":["TOEIC"],"meaningKo":"분석하다"},
  {"word":"announce","pos":["v"],"level":["TOEIC"],"meaningKo":"발표하다"},
  {"word":"annual","pos":["adj"],"level":["TOEIC"],"meaningKo":"연례의"},
  {"word":"anticipate","pos":["v"],"level":["TOEIC"],"meaningKo":"예상하다"},
  {"word":"apologize","pos":["v"],"level":["TOEIC"],"meaningKo":"사과하다"},
  {"word":"apparent","pos":["adj"],"level":["TOEIC"],"meaningKo":"분명한"},
  {"word":"appeal","pos":["n","v"],"level":["TOEIC"],"meaningKo":"호소; 매력"},
  {"word":"apply","pos":["v"],"level":["TOEIC"],"meaningKo":"신청하다; 적용하다"},
  {"word":"appoint","pos":["v"],"level":["TOEIC"],"meaningKo":"임명하다"},
  {"word":"appreciate","pos":["v"],"level":["TOEIC"],"meaningKo":"감사하다; 인식하다"},
  {"word":"approach","pos":["n","v"],"level":["TOEIC"],"meaningKo":"접근; 다가가다"},
  {"word":"appropriate","pos":["adj"],"level":["TOEIC"],"meaningKo":"적절한"},
  {"word":"approve","pos":["v"],"level":["TOEIC"],"meaningKo":"승인하다"},
  {"word":"arrange","pos":["v"],"level":["TOEIC"],"meaningKo":"배열하다; 준비하다"},
  {"word":"arrive","pos":["v"],"level":["TOEIC"],"meaningKo":"도착하다"},
  {"word":"article","pos":["n"],"level":["TOEIC"],"meaningKo":"기사; 조항"},
  {"word":"assemble","pos":["v"],"level":["TOEIC"],"meaningKo":"조립하다; 모이다"},
  {"word":"assess","pos":["v"],"level":["TOEIC"],"meaningKo":"평가하다"},
  {"word":"assign","pos":["v"],"level":["TOEIC"],"meaningKo":"배정하다"},
  {"word":"assist","pos":["v"],"level":["TOEIC"],"meaningKo":"돕다"},
  {"word":"associate","pos":["v","n"],"level":["TOEIC"],"meaningKo":"연관시키다; 동료"},
  {"word":"assume","pos":["v"],"level":["TOEIC"],"meaningKo":"추정하다; 맡다"},
  {"word":"assure","pos":["v"],"level":["TOEIC"],"meaningKo":"보장하다"},
  {"word":"attach","pos":["v"],"level":["TOEIC"],"meaningKo":"첨부하다"},
  {"word":"attend","pos":["v"],"level":["TOEIC"],"meaningKo":"참석하다"},
  {"word":"attention","pos":["n"],"level":["TOEIC"],"meaningKo":"주의; 관심"},
  {"word":"attract","pos":["v"],"level":["TOEIC"],"meaningKo":"끌다; 매혹하다"},
  {"word":"authority","pos":["n"],"level":["TOEIC"],"meaningKo":"권한; 당국"},
  {"word":"available","pos":["adj"],"level":["TOEIC"],"meaningKo":"이용 가능한"},
  {"word":"average","pos":["n","adj"],"level":["TOEIC"],"meaningKo":"평균"},
  {"word":"avoid","pos":["v"],"level":["TOEIC"],"meaningKo":"피하다"},
  {"word":"balance","pos":["n","v"],"level":["TOEIC"],"meaningKo":"균형; 잔액"},
  {"word":"ban","pos":["v","n"],"level":["TOEIC"],"meaningKo":"금지하다"},
  {"word":"base","pos":["n","v"],"level":["TOEIC"],"meaningKo":"기초; 기반을 두다"},
  {"word":"basis","pos":["n"],"level":["TOEIC"],"meaningKo":"기초; 근거"},
  {"word":"behalf","pos":["n"],"level":["TOEIC"],"meaningKo":"~을 대표하여"},
  {"word":"benefit","pos":["n","v"],"level":["TOEIC"],"meaningKo":"혜택; 이익"},
  {"word":"bid","pos":["n","v"],"level":["TOEIC"],"meaningKo":"입찰; 시도"},
  {"word":"board","pos":["n","v"],"level":["TOEIC"],"meaningKo":"이사회; 탑승하다"},
  {"word":"book","pos":["v","n"],"level":["TOEIC"],"meaningKo":"예약하다; 책"},
  {"word":"branch","pos":["n"],"level":["TOEIC"],"meaningKo":"지점; 가지"},
  {"word":"brand","pos":["n"],"level":["TOEIC"],"meaningKo":"브랜드; 상표"},
  {"word":"brief","pos":["adj","n"],"level":["TOEIC"],"meaningKo":"간략한; 요약"},
  {"word":"brochure","pos":["n"],"level":["TOEIC"],"meaningKo":"안내 책자"},
  {"word":"budget","pos":["n"],"level":["TOEIC"],"meaningKo":"예산"},
  {"word":"candidate","pos":["n"],"level":["TOEIC"],"meaningKo":"후보자"},
  {"word":"capacity","pos":["n"],"level":["TOEIC"],"meaningKo":"용량; 능력"},
  {"word":"career","pos":["n"],"level":["TOEIC"],"meaningKo":"경력; 직업"},
  {"word":"category","pos":["n"],"level":["TOEIC"],"meaningKo":"범주; 카테고리"},
  {"word":"cause","pos":["n","v"],"level":["TOEIC"],"meaningKo":"원인; 초래하다"},
  {"word":"celebrate","pos":["v"],"level":["TOEIC"],"meaningKo":"축하하다"},
  {"word":"certificate","pos":["n"],"level":["TOEIC"],"meaningKo":"증명서; 자격증"},
  {"word":"challenge","pos":["n","v"],"level":["TOEIC"],"meaningKo":"도전"},
  {"word":"charge","pos":["n","v"],"level":["TOEIC"],"meaningKo":"요금; 청구하다"},
  {"word":"claim","pos":["v","n"],"level":["TOEIC"],"meaningKo":"주장하다; 청구"},
  {"word":"clarify","pos":["v"],"level":["TOEIC"],"meaningKo":"명확히 하다"},
  {"word":"client","pos":["n"],"level":["TOEIC"],"meaningKo":"고객; 의뢰인"},
  {"word":"collaborate","pos":["v"],"level":["TOEIC"],"meaningKo":"협력하다"},
  {"word":"collect","pos":["v"],"level":["TOEIC"],"meaningKo":"모으다; 수집하다"},
  {"word":"comment","pos":["n","v"],"level":["TOEIC"],"meaningKo":"논평; 의견"},
  {"word":"commit","pos":["v"],"level":["TOEIC"],"meaningKo":"전념하다; 저지르다"},
  {"word":"committee","pos":["n"],"level":["TOEIC"],"meaningKo":"위원회"},
  {"word":"communicate","pos":["v"],"level":["TOEIC"],"meaningKo":"소통하다"},
  {"word":"community","pos":["n"],"level":["TOEIC"],"meaningKo":"지역사회; 공동체"},
  {"word":"compare","pos":["v"],"level":["TOEIC"],"meaningKo":"비교하다"},
  {"word":"compensate","pos":["v"],"level":["TOEIC"],"meaningKo":"보상하다"},
  {"word":"compete","pos":["v"],"level":["TOEIC"],"meaningKo":"경쟁하다"},
  {"word":"complain","pos":["v"],"level":["TOEIC"],"meaningKo":"불평하다"},
  {"word":"complete","pos":["v","adj"],"level":["TOEIC"],"meaningKo":"완료하다; 완전한"},
  {"word":"complex","pos":["adj","n"],"level":["TOEIC"],"meaningKo":"복잡한; 단지"},
  {"word":"comply","pos":["v"],"level":["TOEIC"],"meaningKo":"준수하다"},
  {"word":"comprehensive","pos":["adj"],"level":["TOEIC"],"meaningKo":"포괄적인"},
  {"word":"concern","pos":["n","v"],"level":["TOEIC"],"meaningKo":"우려; 관련되다"},
  {"word":"conclude","pos":["v"],"level":["TOEIC"],"meaningKo":"결론짓다"},
  {"word":"condition","pos":["n"],"level":["TOEIC"],"meaningKo":"조건; 상태"},
  {"word":"conduct","pos":["v","n"],"level":["TOEIC"],"meaningKo":"수행하다; 행위"},
  {"word":"conference","pos":["n"],"level":["TOEIC"],"meaningKo":"회의; 학회"},
  {"word":"confident","pos":["adj"],"level":["TOEIC"],"meaningKo":"자신감 있는"},
  {"word":"confirm","pos":["v"],"level":["TOEIC"],"meaningKo":"확인하다"},
  {"word":"consequence","pos":["n"],"level":["TOEIC"],"meaningKo":"결과; 영향"},
  {"word":"consider","pos":["v"],"level":["TOEIC"],"meaningKo":"고려하다"},
  {"word":"consist","pos":["v"],"level":["TOEIC"],"meaningKo":"구성되다"},
  {"word":"constant","pos":["adj"],"level":["TOEIC"],"meaningKo":"일정한; 끊임없는"},
  {"word":"construct","pos":["v"],"level":["TOEIC"],"meaningKo":"건설하다"},
  {"word":"consult","pos":["v"],"level":["TOEIC"],"meaningKo":"상담하다"},
  {"word":"consumer","pos":["n"],"level":["TOEIC"],"meaningKo":"소비자"},
  {"word":"contact","pos":["n","v"],"level":["TOEIC"],"meaningKo":"연락하다; 접촉"},
  {"word":"contain","pos":["v"],"level":["TOEIC"],"meaningKo":"포함하다"},
  {"word":"content","pos":["n","adj"],"level":["TOEIC"],"meaningKo":"내용; 만족하는"},
  {"word":"contract","pos":["n","v"],"level":["TOEIC"],"meaningKo":"계약"},
  {"word":"contribute","pos":["v"],"level":["TOEIC"],"meaningKo":"기여하다"},
  {"word":"control","pos":["n","v"],"level":["TOEIC"],"meaningKo":"통제; 관리하다"},
  {"word":"convenient","pos":["adj"],"level":["TOEIC"],"meaningKo":"편리한"},
  {"word":"convince","pos":["v"],"level":["TOEIC"],"meaningKo":"납득시키다"},
  {"word":"cooperate","pos":["v"],"level":["TOEIC"],"meaningKo":"협력하다"},
  {"word":"coordinate","pos":["v"],"level":["TOEIC"],"meaningKo":"조율하다"},
  {"word":"corporate","pos":["adj"],"level":["TOEIC"],"meaningKo":"기업의"},
  {"word":"correct","pos":["adj","v"],"level":["TOEIC"],"meaningKo":"올바른; 수정하다"},
  {"word":"correspond","pos":["v"],"level":["TOEIC"],"meaningKo":"일치하다; 서신하다"},
  {"word":"cost","pos":["n","v"],"level":["TOEIC"],"meaningKo":"비용; 들다"},
  {"word":"create","pos":["v"],"level":["TOEIC"],"meaningKo":"만들다; 창조하다"},
  {"word":"criteria","pos":["n"],"level":["TOEIC"],"meaningKo":"기준"},
  {"word":"critical","pos":["adj"],"level":["TOEIC"],"meaningKo":"중요한; 비판적인"},
  {"word":"current","pos":["adj","n"],"level":["TOEIC"],"meaningKo":"현재의; 흐름"},
  {"word":"customer","pos":["n"],"level":["TOEIC"],"meaningKo":"고객"},
  {"word":"deadline","pos":["n"],"level":["TOEIC"],"meaningKo":"마감일"},
  {"word":"deal","pos":["n","v"],"level":["TOEIC"],"meaningKo":"거래; 다루다"},
  {"word":"decade","pos":["n"],"level":["TOEIC"],"meaningKo":"10년"},
  {"word":"decide","pos":["v"],"level":["TOEIC"],"meaningKo":"결정하다"},
  {"word":"decline","pos":["v","n"],"level":["TOEIC"],"meaningKo":"감소하다; 거절하다"},
  {"word":"dedicate","pos":["v"],"level":["TOEIC"],"meaningKo":"전념하다; 헌신하다"},
  {"word":"define","pos":["v"],"level":["TOEIC"],"meaningKo":"정의하다"},
  {"word":"delay","pos":["n","v"],"level":["TOEIC"],"meaningKo":"지연"},
  {"word":"delegate","pos":["v","n"],"level":["TOEIC"],"meaningKo":"위임하다; 대표"},
  {"word":"deliver","pos":["v"],"level":["TOEIC"],"meaningKo":"배달하다; 전달하다"},
  {"word":"demand","pos":["n","v"],"level":["TOEIC"],"meaningKo":"수요; 요구하다"},
  {"word":"demonstrate","pos":["v"],"level":["TOEIC"],"meaningKo":"보여주다; 시연하다"},
  {"word":"department","pos":["n"],"level":["TOEIC"],"meaningKo":"부서"},
  {"word":"depend","pos":["v"],"level":["TOEIC"],"meaningKo":"의존하다"},
  {"word":"deposit","pos":["n","v"],"level":["TOEIC"],"meaningKo":"보증금; 입금하다"},
  {"word":"describe","pos":["v"],"level":["TOEIC"],"meaningKo":"묘사하다"},
  {"word":"design","pos":["n","v"],"level":["TOEIC"],"meaningKo":"디자인; 설계하다"},
  {"word":"detail","pos":["n"],"level":["TOEIC"],"meaningKo":"세부사항"},
  {"word":"determine","pos":["v"],"level":["TOEIC"],"meaningKo":"결정하다; 확인하다"},
  {"word":"develop","pos":["v"],"level":["TOEIC"],"meaningKo":"개발하다"},
  {"word":"device","pos":["n"],"level":["TOEIC"],"meaningKo":"장치; 기기"},
  {"word":"differ","pos":["v"],"level":["TOEIC"],"meaningKo":"다르다"},
  {"word":"direct","pos":["adj","v"],"level":["TOEIC"],"meaningKo":"직접적인; 지시하다"},
  {"word":"director","pos":["n"],"level":["TOEIC"],"meaningKo":"이사; 감독"},
  {"word":"disappoint","pos":["v"],"level":["TOEIC"],"meaningKo":"실망시키다"},
  {"word":"discount","pos":["n","v"],"level":["TOEIC"],"meaningKo":"할인"},
  {"word":"discover","pos":["v"],"level":["TOEIC"],"meaningKo":"발견하다"},
  {"word":"discuss","pos":["v"],"level":["TOEIC"],"meaningKo":"논의하다"},
  {"word":"display","pos":["n","v"],"level":["TOEIC"],"meaningKo":"전시; 보여주다"},
  {"word":"distribute","pos":["v"],"level":["TOEIC"],"meaningKo":"배포하다"},
  {"word":"document","pos":["n","v"],"level":["TOEIC"],"meaningKo":"문서; 기록하다"},
  {"word":"domestic","pos":["adj"],"level":["TOEIC"],"meaningKo":"국내의"},
  {"word":"donate","pos":["v"],"level":["TOEIC"],"meaningKo":"기부하다"},
  {"word":"due","pos":["adj"],"level":["TOEIC"],"meaningKo":"~때문에; 예정인"},
  {"word":"duration","pos":["n"],"level":["TOEIC"],"meaningKo":"기간"},
  {"word":"earn","pos":["v"],"level":["TOEIC"],"meaningKo":"벌다"},
  {"word":"economy","pos":["n"],"level":["TOEIC"],"meaningKo":"경제"},
  {"word":"effect","pos":["n"],"level":["TOEIC"],"meaningKo":"효과; 영향"},
  {"word":"efficient","pos":["adj"],"level":["TOEIC"],"meaningKo":"효율적인"},
  {"word":"effort","pos":["n"],"level":["TOEIC"],"meaningKo":"노력"},
  {"word":"eligible","pos":["adj"],"level":["TOEIC"],"meaningKo":"자격이 있는"},
  {"word":"eliminate","pos":["v"],"level":["TOEIC"],"meaningKo":"제거하다"},
  {"word":"emergency","pos":["n"],"level":["TOEIC"],"meaningKo":"비상; 응급"},
  {"word":"emphasis","pos":["n"],"level":["TOEIC"],"meaningKo":"강조"},
  {"word":"employ","pos":["v"],"level":["TOEIC"],"meaningKo":"고용하다"},
  {"word":"enable","pos":["v"],"level":["TOEIC"],"meaningKo":"가능하게 하다"},
  {"word":"encounter","pos":["v","n"],"level":["TOEIC"],"meaningKo":"마주치다"},
  {"word":"encourage","pos":["v"],"level":["TOEIC"],"meaningKo":"격려하다"},
  {"word":"engage","pos":["v"],"level":["TOEIC"],"meaningKo":"참여하다"},
  {"word":"enhance","pos":["v"],"level":["TOEIC"],"meaningKo":"향상시키다"},
  {"word":"enormous","pos":["adj"],"level":["TOEIC"],"meaningKo":"거대한"},
  {"word":"ensure","pos":["v"],"level":["TOEIC"],"meaningKo":"보장하다"},
  {"word":"enterprise","pos":["n"],"level":["TOEIC"],"meaningKo":"기업; 사업"},
  {"word":"entire","pos":["adj"],"level":["TOEIC"],"meaningKo":"전체의"},
  {"word":"environment","pos":["n"],"level":["TOEIC"],"meaningKo":"환경"},
  {"word":"equipment","pos":["n"],"level":["TOEIC"],"meaningKo":"장비"},
  {"word":"equivalent","pos":["adj","n"],"level":["TOEIC"],"meaningKo":"동등한"},
  {"word":"essential","pos":["adj"],"level":["TOEIC"],"meaningKo":"필수적인"},
  {"word":"establish","pos":["v"],"level":["TOEIC"],"meaningKo":"설립하다"},
  {"word":"estimate","pos":["v","n"],"level":["TOEIC"],"meaningKo":"추정하다"},
  {"word":"evaluate","pos":["v"],"level":["TOEIC"],"meaningKo":"평가하다"},
  {"word":"event","pos":["n"],"level":["TOEIC"],"meaningKo":"행사; 사건"},
  {"word":"evidence","pos":["n"],"level":["TOEIC"],"meaningKo":"증거"},
  {"word":"exact","pos":["adj"],"level":["TOEIC"],"meaningKo":"정확한"},
  {"word":"examine","pos":["v"],"level":["TOEIC"],"meaningKo":"검사하다"},
  {"word":"exceed","pos":["v"],"level":["TOEIC"],"meaningKo":"초과하다"},
  {"word":"excellent","pos":["adj"],"level":["TOEIC"],"meaningKo":"훌륭한"},
  {"word":"exchange","pos":["n","v"],"level":["TOEIC"],"meaningKo":"교환"},
  {"word":"exclude","pos":["v"],"level":["TOEIC"],"meaningKo":"제외하다"},
  {"word":"executive","pos":["n","adj"],"level":["TOEIC"],"meaningKo":"임원; 경영의"},
  {"word":"exhibit","pos":["v","n"],"level":["TOEIC"],"meaningKo":"전시하다"},
  {"word":"expand","pos":["v"],"level":["TOEIC"],"meaningKo":"확장하다"},
  {"word":"expect","pos":["v"],"level":["TOEIC"],"meaningKo":"기대하다"},
  {"word":"expenditure","pos":["n"],"level":["TOEIC"],"meaningKo":"지출"},
  {"word":"expense","pos":["n"],"level":["TOEIC"],"meaningKo":"비용"},
  {"word":"experience","pos":["n","v"],"level":["TOEIC"],"meaningKo":"경험"},
  {"word":"expert","pos":["n","adj"],"level":["TOEIC"],"meaningKo":"전문가"},
  {"word":"expire","pos":["v"],"level":["TOEIC"],"meaningKo":"만료되다"},
  {"word":"explain","pos":["v"],"level":["TOEIC"],"meaningKo":"설명하다"},
  {"word":"export","pos":["v","n"],"level":["TOEIC"],"meaningKo":"수출하다"},
  {"word":"extend","pos":["v"],"level":["TOEIC"],"meaningKo":"연장하다"},
  {"word":"extensive","pos":["adj"],"level":["TOEIC"],"meaningKo":"광범위한"},
  {"word":"external","pos":["adj"],"level":["TOEIC"],"meaningKo":"외부의"},
  {"word":"extra","pos":["adj"],"level":["TOEIC"],"meaningKo":"추가의; 여분의"},
  {"word":"facility","pos":["n"],"level":["TOEIC"],"meaningKo":"시설"},
  {"word":"factor","pos":["n"],"level":["TOEIC"],"meaningKo":"요인"},
  {"word":"familiar","pos":["adj"],"level":["TOEIC"],"meaningKo":"익숙한"},
  {"word":"feature","pos":["n","v"],"level":["TOEIC"],"meaningKo":"특징; 포함하다"},
  {"word":"feedback","pos":["n"],"level":["TOEIC"],"meaningKo":"피드백"},
  {"word":"figure","pos":["n","v"],"level":["TOEIC"],"meaningKo":"수치; 인물"},
  {"word":"final","pos":["adj"],"level":["TOEIC"],"meaningKo":"최종의"},
  {"word":"finance","pos":["n","v"],"level":["TOEIC"],"meaningKo":"재정; 자금 조달하다"},
  {"word":"flexible","pos":["adj"],"level":["TOEIC"],"meaningKo":"유연한"},
  {"word":"focus","pos":["n","v"],"level":["TOEIC"],"meaningKo":"집중; 초점"},
  {"word":"follow","pos":["v"],"level":["TOEIC"],"meaningKo":"따르다"},
  {"word":"forecast","pos":["n","v"],"level":["TOEIC"],"meaningKo":"예측"},
  {"word":"formal","pos":["adj"],"level":["TOEIC"],"meaningKo":"공식적인"},
  {"word":"former","pos":["adj"],"level":["TOEIC"],"meaningKo":"이전의"},
  {"word":"forward","pos":["adv","v"],"level":["TOEIC"],"meaningKo":"앞으로; 전달하다"},
  {"word":"foundation","pos":["n"],"level":["TOEIC"],"meaningKo":"재단; 기초"},
  {"word":"frequent","pos":["adj"],"level":["TOEIC"],"meaningKo":"빈번한"},
  {"word":"fulfill","pos":["v"],"level":["TOEIC"],"meaningKo":"이행하다"},
  {"word":"fund","pos":["n","v"],"level":["TOEIC"],"meaningKo":"기금; 자금 제공하다"},
  {"word":"furniture","pos":["n"],"level":["TOEIC"],"meaningKo":"가구"},
  {"word":"gain","pos":["v","n"],"level":["TOEIC"],"meaningKo":"얻다; 이익"},
  {"word":"generate","pos":["v"],"level":["TOEIC"],"meaningKo":"생성하다"},
  {"word":"goal","pos":["n"],"level":["TOEIC"],"meaningKo":"목표"},
  {"word":"grant","pos":["v","n"],"level":["TOEIC"],"meaningKo":"승인하다; 보조금"},
  {"word":"guarantee","pos":["n","v"],"level":["TOEIC"],"meaningKo":"보증"},
  {"word":"guide","pos":["n","v"],"level":["TOEIC"],"meaningKo":"안내; 지도하다"},
  {"word":"headquarters","pos":["n"],"level":["TOEIC"],"meaningKo":"본사"},
  {"word":"hire","pos":["v"],"level":["TOEIC"],"meaningKo":"고용하다"},
  {"word":"identify","pos":["v"],"level":["TOEIC"],"meaningKo":"확인하다; 식별하다"},
  {"word":"illustrate","pos":["v"],"level":["TOEIC"],"meaningKo":"설명하다; 삽화를 넣다"},
  {"word":"impact","pos":["n","v"],"level":["TOEIC"],"meaningKo":"영향; 충격"},
  {"word":"implement","pos":["v"],"level":["TOEIC"],"meaningKo":"이행하다; 실행하다"},
  {"word":"import","pos":["v","n"],"level":["TOEIC"],"meaningKo":"수입하다"},
  {"word":"impose","pos":["v"],"level":["TOEIC"],"meaningKo":"부과하다"},
  {"word":"impress","pos":["v"],"level":["TOEIC"],"meaningKo":"감동시키다"},
  {"word":"improve","pos":["v"],"level":["TOEIC"],"meaningKo":"개선하다"},
  {"word":"incentive","pos":["n"],"level":["TOEIC"],"meaningKo":"인센티브; 동기"},
  {"word":"include","pos":["v"],"level":["TOEIC"],"meaningKo":"포함하다"},
  {"word":"income","pos":["n"],"level":["TOEIC"],"meaningKo":"소득"},
  {"word":"increase","pos":["v","n"],"level":["TOEIC"],"meaningKo":"증가하다"},
  {"word":"indicate","pos":["v"],"level":["TOEIC"],"meaningKo":"나타내다"},
  {"word":"individual","pos":["n","adj"],"level":["TOEIC"],"meaningKo":"개인; 개별적인"},
  {"word":"industry","pos":["n"],"level":["TOEIC"],"meaningKo":"산업"},
  {"word":"influence","pos":["n","v"],"level":["TOEIC"],"meaningKo":"영향"},
  {"word":"inform","pos":["v"],"level":["TOEIC"],"meaningKo":"알리다"},
  {"word":"initial","pos":["adj"],"level":["TOEIC"],"meaningKo":"초기의"},
  {"word":"initiative","pos":["n"],"level":["TOEIC"],"meaningKo":"주도; 계획"},
  {"word":"inquire","pos":["v"],"level":["TOEIC"],"meaningKo":"문의하다"},
  {"word":"inspect","pos":["v"],"level":["TOEIC"],"meaningKo":"검사하다"},
  {"word":"install","pos":["v"],"level":["TOEIC"],"meaningKo":"설치하다"},
  {"word":"institution","pos":["n"],"level":["TOEIC"],"meaningKo":"기관"},
  {"word":"instruct","pos":["v"],"level":["TOEIC"],"meaningKo":"지시하다"},
  {"word":"insurance","pos":["n"],"level":["TOEIC"],"meaningKo":"보험"},
  {"word":"intend","pos":["v"],"level":["TOEIC"],"meaningKo":"의도하다"},
  {"word":"interest","pos":["n"],"level":["TOEIC"],"meaningKo":"관심; 이자"},
  {"word":"internal","pos":["adj"],"level":["TOEIC"],"meaningKo":"내부의"},
  {"word":"interpret","pos":["v"],"level":["TOEIC"],"meaningKo":"해석하다; 통역하다"},
  {"word":"introduce","pos":["v"],"level":["TOEIC"],"meaningKo":"소개하다"},
  {"word":"inventory","pos":["n"],"level":["TOEIC"],"meaningKo":"재고"},
  {"word":"invest","pos":["v"],"level":["TOEIC"],"meaningKo":"투자하다"},
  {"word":"investigate","pos":["v"],"level":["TOEIC"],"meaningKo":"조사하다"},
  {"word":"invoice","pos":["n"],"level":["TOEIC"],"meaningKo":"송장; 청구서"},
  {"word":"involve","pos":["v"],"level":["TOEIC"],"meaningKo":"포함하다; 관련되다"},
  {"word":"issue","pos":["n","v"],"level":["TOEIC"],"meaningKo":"문제; 발행하다"},
  {"word":"item","pos":["n"],"level":["TOEIC"],"meaningKo":"항목; 물품"},
  {"word":"journey","pos":["n"],"level":["TOEIC"],"meaningKo":"여행"},
  {"word":"judge","pos":["v","n"],"level":["TOEIC"],"meaningKo":"판단하다; 판사"},
  {"word":"labor","pos":["n"],"level":["TOEIC"],"meaningKo":"노동"},
  {"word":"lack","pos":["n","v"],"level":["TOEIC"],"meaningKo":"부족"},
  {"word":"launch","pos":["v","n"],"level":["TOEIC"],"meaningKo":"출시하다"},
  {"word":"lead","pos":["v","n"],"level":["TOEIC"],"meaningKo":"이끌다"},
  {"word":"lease","pos":["n","v"],"level":["TOEIC"],"meaningKo":"임대"},
  {"word":"legal","pos":["adj"],"level":["TOEIC"],"meaningKo":"법적인"},
  {"word":"legislation","pos":["n"],"level":["TOEIC"],"meaningKo":"법률; 입법"},
  {"word":"limit","pos":["n","v"],"level":["TOEIC"],"meaningKo":"제한"},
  {"word":"locate","pos":["v"],"level":["TOEIC"],"meaningKo":"위치하다; 찾다"},
  {"word":"luggage","pos":["n"],"level":["TOEIC"],"meaningKo":"짐; 수하물"},
  {"word":"maintain","pos":["v"],"level":["TOEIC"],"meaningKo":"유지하다"},
  {"word":"major","pos":["adj"],"level":["TOEIC"],"meaningKo":"주요한"},
  {"word":"manage","pos":["v"],"level":["TOEIC"],"meaningKo":"관리하다"},
  {"word":"manner","pos":["n"],"level":["TOEIC"],"meaningKo":"방식; 태도"},
  {"word":"manufacture","pos":["v","n"],"level":["TOEIC"],"meaningKo":"제조하다"},
  {"word":"market","pos":["n","v"],"level":["TOEIC"],"meaningKo":"시장; 판매하다"},
  {"word":"material","pos":["n","adj"],"level":["TOEIC"],"meaningKo":"재료; 물질적인"},
  {"word":"matter","pos":["n","v"],"level":["TOEIC"],"meaningKo":"문제; 중요하다"},
  {"word":"measure","pos":["n","v"],"level":["TOEIC"],"meaningKo":"조치; 측정하다"},
  {"word":"medication","pos":["n"],"level":["TOEIC"],"meaningKo":"약물"},
  {"word":"mention","pos":["v","n"],"level":["TOEIC"],"meaningKo":"언급하다"},
  {"word":"merchandise","pos":["n"],"level":["TOEIC"],"meaningKo":"상품"},
  {"word":"merge","pos":["v"],"level":["TOEIC"],"meaningKo":"합병하다"},
  {"word":"method","pos":["n"],"level":["TOEIC"],"meaningKo":"방법"},
  {"word":"minimum","pos":["n","adj"],"level":["TOEIC"],"meaningKo":"최소"},
  {"word":"modify","pos":["v"],"level":["TOEIC"],"meaningKo":"수정하다"},
  {"word":"monitor","pos":["v","n"],"level":["TOEIC"],"meaningKo":"감시하다"},
  {"word":"mortgage","pos":["n"],"level":["TOEIC"],"meaningKo":"담보 대출"},
  {"word":"motivate","pos":["v"],"level":["TOEIC"],"meaningKo":"동기를 부여하다"},
  {"word":"negotiate","pos":["v"],"level":["TOEIC"],"meaningKo":"협상하다"},
  {"word":"network","pos":["n"],"level":["TOEIC"],"meaningKo":"네트워크; 인맥"},
  {"word":"nominate","pos":["v"],"level":["TOEIC"],"meaningKo":"지명하다"},
  {"word":"note","pos":["n","v"],"level":["TOEIC"],"meaningKo":"메모; 주목하다"},
  {"word":"notice","pos":["n","v"],"level":["TOEIC"],"meaningKo":"공지; 알아차리다"},
  {"word":"notify","pos":["v"],"level":["TOEIC"],"meaningKo":"통보하다"},
  {"word":"objective","pos":["n","adj"],"level":["TOEIC"],"meaningKo":"목표; 객관적인"},
  {"word":"obligation","pos":["n"],"level":["TOEIC"],"meaningKo":"의무"},
  {"word":"observe","pos":["v"],"level":["TOEIC"],"meaningKo":"관찰하다"},
  {"word":"obtain","pos":["v"],"level":["TOEIC"],"meaningKo":"얻다"},
  {"word":"occasion","pos":["n"],"level":["TOEIC"],"meaningKo":"경우; 행사"},
  {"word":"occupy","pos":["v"],"level":["TOEIC"],"meaningKo":"차지하다"},
  {"word":"occur","pos":["v"],"level":["TOEIC"],"meaningKo":"발생하다"},
  {"word":"offer","pos":["v","n"],"level":["TOEIC"],"meaningKo":"제공하다"},
  {"word":"official","pos":["adj","n"],"level":["TOEIC"],"meaningKo":"공식적인"},
  {"word":"operate","pos":["v"],"level":["TOEIC"],"meaningKo":"운영하다"},
  {"word":"opinion","pos":["n"],"level":["TOEIC"],"meaningKo":"의견"},
  {"word":"opportunity","pos":["n"],"level":["TOEIC"],"meaningKo":"기회"},
  {"word":"option","pos":["n"],"level":["TOEIC"],"meaningKo":"선택; 옵션"},
  {"word":"order","pos":["n","v"],"level":["TOEIC"],"meaningKo":"주문; 명령하다"},
  {"word":"organize","pos":["v"],"level":["TOEIC"],"meaningKo":"조직하다"},
  {"word":"original","pos":["adj"],"level":["TOEIC"],"meaningKo":"원래의; 독창적인"},
  {"word":"outline","pos":["n","v"],"level":["TOEIC"],"meaningKo":"개요; 윤곽"},
  {"word":"outstanding","pos":["adj"],"level":["TOEIC"],"meaningKo":"뛰어난; 미결제의"},
  {"word":"overall","pos":["adj","adv"],"level":["TOEIC"],"meaningKo":"전반적인"},
  {"word":"overcome","pos":["v"],"level":["TOEIC"],"meaningKo":"극복하다"},
  {"word":"overlook","pos":["v"],"level":["TOEIC"],"meaningKo":"간과하다"},
  {"word":"participate","pos":["v"],"level":["TOEIC"],"meaningKo":"참여하다"},
  {"word":"particular","pos":["adj"],"level":["TOEIC"],"meaningKo":"특정한"},
  {"word":"patient","pos":["n","adj"],"level":["TOEIC"],"meaningKo":"환자; 참을성 있는"},
  {"word":"payment","pos":["n"],"level":["TOEIC"],"meaningKo":"지불"},
  {"word":"penalty","pos":["n"],"level":["TOEIC"],"meaningKo":"벌금; 처벌"},
  {"word":"perform","pos":["v"],"level":["TOEIC"],"meaningKo":"수행하다; 공연하다"},
  {"word":"permanent","pos":["adj"],"level":["TOEIC"],"meaningKo":"영구적인"},
  {"word":"permit","pos":["v","n"],"level":["TOEIC"],"meaningKo":"허가하다"},
  {"word":"persuade","pos":["v"],"level":["TOEIC"],"meaningKo":"설득하다"},
  {"word":"phase","pos":["n"],"level":["TOEIC"],"meaningKo":"단계"},
  {"word":"policy","pos":["n"],"level":["TOEIC"],"meaningKo":"정책"},
  {"word":"portion","pos":["n"],"level":["TOEIC"],"meaningKo":"부분; 1인분"},
  {"word":"position","pos":["n"],"level":["TOEIC"],"meaningKo":"위치; 직위"},
  {"word":"postpone","pos":["v"],"level":["TOEIC"],"meaningKo":"연기하다"},
  {"word":"potential","pos":["adj","n"],"level":["TOEIC"],"meaningKo":"잠재적인"},
  {"word":"practice","pos":["n","v"],"level":["TOEIC"],"meaningKo":"연습; 실행"},
  {"word":"predict","pos":["v"],"level":["TOEIC"],"meaningKo":"예측하다"},
  {"word":"prefer","pos":["v"],"level":["TOEIC"],"meaningKo":"선호하다"},
  {"word":"prepare","pos":["v"],"level":["TOEIC"],"meaningKo":"준비하다"},
  {"word":"present","pos":["v","n","adj"],"level":["TOEIC"],"meaningKo":"발표하다; 선물; 현재의"},
  {"word":"preserve","pos":["v"],"level":["TOEIC"],"meaningKo":"보존하다"},
  {"word":"prevent","pos":["v"],"level":["TOEIC"],"meaningKo":"방지하다"},
  {"word":"previous","pos":["adj"],"level":["TOEIC"],"meaningKo":"이전의"},
  {"word":"primary","pos":["adj"],"level":["TOEIC"],"meaningKo":"주요한; 기초적인"},
  {"word":"principal","pos":["adj","n"],"level":["TOEIC"],"meaningKo":"주요한; 교장"},
  {"word":"priority","pos":["n"],"level":["TOEIC"],"meaningKo":"우선순위"},
  {"word":"procedure","pos":["n"],"level":["TOEIC"],"meaningKo":"절차"},
  {"word":"proceed","pos":["v"],"level":["TOEIC"],"meaningKo":"진행하다"},
  {"word":"process","pos":["n","v"],"level":["TOEIC"],"meaningKo":"과정; 처리하다"},
  {"word":"produce","pos":["v"],"level":["TOEIC"],"meaningKo":"생산하다"},
  {"word":"product","pos":["n"],"level":["TOEIC"],"meaningKo":"제품"},
  {"word":"profession","pos":["n"],"level":["TOEIC"],"meaningKo":"직업"},
  {"word":"profit","pos":["n"],"level":["TOEIC"],"meaningKo":"이익"},
  {"word":"program","pos":["n"],"level":["TOEIC"],"meaningKo":"프로그램"},
  {"word":"progress","pos":["n","v"],"level":["TOEIC"],"meaningKo":"진전"},
  {"word":"project","pos":["n"],"level":["TOEIC"],"meaningKo":"프로젝트"},
  {"word":"promote","pos":["v"],"level":["TOEIC"],"meaningKo":"홍보하다; 승진시키다"},
  {"word":"prompt","pos":["adj","v"],"level":["TOEIC"],"meaningKo":"신속한; 촉구하다"},
  {"word":"proper","pos":["adj"],"level":["TOEIC"],"meaningKo":"적절한"},
  {"word":"property","pos":["n"],"level":["TOEIC"],"meaningKo":"재산; 부동산"},
  {"word":"proposal","pos":["n"],"level":["TOEIC"],"meaningKo":"제안"},
  {"word":"prospect","pos":["n"],"level":["TOEIC"],"meaningKo":"전망; 가능성"},
  {"word":"protect","pos":["v"],"level":["TOEIC"],"meaningKo":"보호하다"},
  {"word":"provide","pos":["v"],"level":["TOEIC"],"meaningKo":"제공하다"},
  {"word":"publication","pos":["n"],"level":["TOEIC"],"meaningKo":"출판물"},
  {"word":"purchase","pos":["v","n"],"level":["TOEIC"],"meaningKo":"구매하다"},
  {"word":"pursue","pos":["v"],"level":["TOEIC"],"meaningKo":"추구하다"},
  {"word":"qualify","pos":["v"],"level":["TOEIC"],"meaningKo":"자격을 얻다"},
  {"word":"quantity","pos":["n"],"level":["TOEIC"],"meaningKo":"양; 수량"},
  {"word":"quarter","pos":["n"],"level":["TOEIC"],"meaningKo":"분기; 4분의 1"},
  {"word":"quote","pos":["v","n"],"level":["TOEIC"],"meaningKo":"인용하다; 견적"},
  {"word":"range","pos":["n","v"],"level":["TOEIC"],"meaningKo":"범위"},
  {"word":"rate","pos":["n"],"level":["TOEIC"],"meaningKo":"비율; 요금"},
  {"word":"realize","pos":["v"],"level":["TOEIC"],"meaningKo":"깨닫다; 실현하다"},
  {"word":"reasonable","pos":["adj"],"level":["TOEIC"],"meaningKo":"합리적인"},
  {"word":"receipt","pos":["n"],"level":["TOEIC"],"meaningKo":"영수증"},
  {"word":"receive","pos":["v"],"level":["TOEIC"],"meaningKo":"받다"},
  {"word":"recognize","pos":["v"],"level":["TOEIC"],"meaningKo":"인식하다"},
  {"word":"recommend","pos":["v"],"level":["TOEIC"],"meaningKo":"추천하다"},
  {"word":"record","pos":["n","v"],"level":["TOEIC"],"meaningKo":"기록"},
  {"word":"recover","pos":["v"],"level":["TOEIC"],"meaningKo":"회복하다"},
  {"word":"recruit","pos":["v","n"],"level":["TOEIC"],"meaningKo":"모집하다"},
  {"word":"reduce","pos":["v"],"level":["TOEIC"],"meaningKo":"줄이다"},
  {"word":"refer","pos":["v"],"level":["TOEIC"],"meaningKo":"참조하다; 언급하다"},
  {"word":"reflect","pos":["v"],"level":["TOEIC"],"meaningKo":"반영하다"},
  {"word":"refund","pos":["n","v"],"level":["TOEIC"],"meaningKo":"환불"},
  {"word":"regard","pos":["v","n"],"level":["TOEIC"],"meaningKo":"간주하다; 관련하여"},
  {"word":"region","pos":["n"],"level":["TOEIC"],"meaningKo":"지역"},
  {"word":"register","pos":["v"],"level":["TOEIC"],"meaningKo":"등록하다"},
  {"word":"regulate","pos":["v"],"level":["TOEIC"],"meaningKo":"규제하다"},
  {"word":"reject","pos":["v"],"level":["TOEIC"],"meaningKo":"거절하다"},
  {"word":"relate","pos":["v"],"level":["TOEIC"],"meaningKo":"관련되다"},
  {"word":"release","pos":["v","n"],"level":["TOEIC"],"meaningKo":"공개하다; 발표"},
  {"word":"relevant","pos":["adj"],"level":["TOEIC"],"meaningKo":"관련 있는"},
  {"word":"reliable","pos":["adj"],"level":["TOEIC"],"meaningKo":"신뢰할 수 있는"},
  {"word":"relocate","pos":["v"],"level":["TOEIC"],"meaningKo":"이전하다"},
  {"word":"remain","pos":["v"],"level":["TOEIC"],"meaningKo":"남다"},
  {"word":"remind","pos":["v"],"level":["TOEIC"],"meaningKo":"상기시키다"},
  {"word":"remove","pos":["v"],"level":["TOEIC"],"meaningKo":"제거하다"},
  {"word":"renew","pos":["v"],"level":["TOEIC"],"meaningKo":"갱신하다"},
  {"word":"renovate","pos":["v"],"level":["TOEIC"],"meaningKo":"보수하다; 개조하다"},
  {"word":"rent","pos":["n","v"],"level":["TOEIC"],"meaningKo":"임대료; 빌리다"},
  {"word":"repair","pos":["v","n"],"level":["TOEIC"],"meaningKo":"수리하다"},
  {"word":"replace","pos":["v"],"level":["TOEIC"],"meaningKo":"교체하다"},
  {"word":"report","pos":["n","v"],"level":["TOEIC"],"meaningKo":"보고서; 보고하다"},
  {"word":"represent","pos":["v"],"level":["TOEIC"],"meaningKo":"대표하다"},
  {"word":"reputation","pos":["n"],"level":["TOEIC"],"meaningKo":"명성"},
  {"word":"request","pos":["n","v"],"level":["TOEIC"],"meaningKo":"요청"},
  {"word":"require","pos":["v"],"level":["TOEIC"],"meaningKo":"요구하다"},
  {"word":"research","pos":["n","v"],"level":["TOEIC"],"meaningKo":"연구"},
  {"word":"reservation","pos":["n"],"level":["TOEIC"],"meaningKo":"예약"},
  {"word":"resident","pos":["n"],"level":["TOEIC"],"meaningKo":"거주자"},
  {"word":"resign","pos":["v"],"level":["TOEIC"],"meaningKo":"사직하다"},
  {"word":"resolve","pos":["v"],"level":["TOEIC"],"meaningKo":"해결하다"},
  {"word":"resource","pos":["n"],"level":["TOEIC"],"meaningKo":"자원"},
  {"word":"respond","pos":["v"],"level":["TOEIC"],"meaningKo":"응답하다"},
  {"word":"responsibility","pos":["n"],"level":["TOEIC"],"meaningKo":"책임"},
  {"word":"restore","pos":["v"],"level":["TOEIC"],"meaningKo":"복원하다"},
  {"word":"restrict","pos":["v"],"level":["TOEIC"],"meaningKo":"제한하다"},
  {"word":"result","pos":["n","v"],"level":["TOEIC"],"meaningKo":"결과"},
  {"word":"retail","pos":["n","adj"],"level":["TOEIC"],"meaningKo":"소매"},
  {"word":"retain","pos":["v"],"level":["TOEIC"],"meaningKo":"유지하다"},
  {"word":"retire","pos":["v"],"level":["TOEIC"],"meaningKo":"은퇴하다"},
  {"word":"revenue","pos":["n"],"level":["TOEIC"],"meaningKo":"수익"},
  {"word":"review","pos":["n","v"],"level":["TOEIC"],"meaningKo":"검토; 리뷰"},
  {"word":"revise","pos":["v"],"level":["TOEIC"],"meaningKo":"수정하다"},
  {"word":"reward","pos":["n","v"],"level":["TOEIC"],"meaningKo":"보상"},
  {"word":"risk","pos":["n","v"],"level":["TOEIC"],"meaningKo":"위험"},
  {"word":"role","pos":["n"],"level":["TOEIC"],"meaningKo":"역할"},
  {"word":"routine","pos":["n","adj"],"level":["TOEIC"],"meaningKo":"일상; 일상적인"},
  {"word":"salary","pos":["n"],"level":["TOEIC"],"meaningKo":"급여"},
  {"word":"sample","pos":["n"],"level":["TOEIC"],"meaningKo":"샘플; 견본"},
  {"word":"satisfy","pos":["v"],"level":["TOEIC"],"meaningKo":"만족시키다"},
  {"word":"schedule","pos":["n","v"],"level":["TOEIC"],"meaningKo":"일정"},
  {"word":"secure","pos":["adj","v"],"level":["TOEIC"],"meaningKo":"안전한; 확보하다"},
  {"word":"select","pos":["v"],"level":["TOEIC"],"meaningKo":"선택하다"},
  {"word":"separate","pos":["v","adj"],"level":["TOEIC"],"meaningKo":"분리하다; 별개의"},
  {"word":"serve","pos":["v"],"level":["TOEIC"],"meaningKo":"봉사하다; 제공하다"},
  {"word":"session","pos":["n"],"level":["TOEIC"],"meaningKo":"회기; 세션"},
  {"word":"settle","pos":["v"],"level":["TOEIC"],"meaningKo":"해결하다; 정착하다"},
  {"word":"severe","pos":["adj"],"level":["TOEIC"],"meaningKo":"심각한"},
  {"word":"share","pos":["v","n"],"level":["TOEIC"],"meaningKo":"공유하다; 주식"},
  {"word":"shift","pos":["n","v"],"level":["TOEIC"],"meaningKo":"교대; 변화"},
  {"word":"significant","pos":["adj"],"level":["TOEIC"],"meaningKo":"중요한; 상당한"},
  {"word":"similar","pos":["adj"],"level":["TOEIC"],"meaningKo":"비슷한"},
  {"word":"situation","pos":["n"],"level":["TOEIC"],"meaningKo":"상황"},
  {"word":"solve","pos":["v"],"level":["TOEIC"],"meaningKo":"해결하다"},
  {"word":"source","pos":["n"],"level":["TOEIC"],"meaningKo":"출처; 원천"},
  {"word":"specific","pos":["adj"],"level":["TOEIC"],"meaningKo":"구체적인"},
  {"word":"sponsor","pos":["n","v"],"level":["TOEIC"],"meaningKo":"후원자; 후원하다"},
  {"word":"standard","pos":["n","adj"],"level":["TOEIC"],"meaningKo":"기준; 표준의"},
  {"word":"statement","pos":["n"],"level":["TOEIC"],"meaningKo":"진술; 명세서"},
  {"word":"status","pos":["n"],"level":["TOEIC"],"meaningKo":"상태; 지위"},
  {"word":"strategy","pos":["n"],"level":["TOEIC"],"meaningKo":"전략"},
  {"word":"strict","pos":["adj"],"level":["TOEIC"],"meaningKo":"엄격한"},
  {"word":"structure","pos":["n"],"level":["TOEIC"],"meaningKo":"구조"},
  {"word":"submit","pos":["v"],"level":["TOEIC"],"meaningKo":"제출하다"},
  {"word":"subscribe","pos":["v"],"level":["TOEIC"],"meaningKo":"구독하다"},
  {"word":"substance","pos":["n"],"level":["TOEIC"],"meaningKo":"물질"},
  {"word":"substitute","pos":["n","v"],"level":["TOEIC"],"meaningKo":"대체하다; 대용품"},
  {"word":"succeed","pos":["v"],"level":["TOEIC"],"meaningKo":"성공하다"},
  {"word":"sufficient","pos":["adj"],"level":["TOEIC"],"meaningKo":"충분한"},
  {"word":"suggest","pos":["v"],"level":["TOEIC"],"meaningKo":"제안하다"},
  {"word":"suitable","pos":["adj"],"level":["TOEIC"],"meaningKo":"적합한"},
  {"word":"summarize","pos":["v"],"level":["TOEIC"],"meaningKo":"요약하다"},
  {"word":"supervise","pos":["v"],"level":["TOEIC"],"meaningKo":"감독하다"},
  {"word":"supply","pos":["n","v"],"level":["TOEIC"],"meaningKo":"공급"},
  {"word":"support","pos":["v","n"],"level":["TOEIC"],"meaningKo":"지원하다"},
  {"word":"surpass","pos":["v"],"level":["TOEIC"],"meaningKo":"능가하다"},
  {"word":"survey","pos":["n","v"],"level":["TOEIC"],"meaningKo":"설문조사"},
  {"word":"sustain","pos":["v"],"level":["TOEIC"],"meaningKo":"유지하다; 지탱하다"},
  {"word":"target","pos":["n","v"],"level":["TOEIC"],"meaningKo":"목표; 대상"},
  {"word":"technical","pos":["adj"],"level":["TOEIC"],"meaningKo":"기술적인"},
  {"word":"temporary","pos":["adj"],"level":["TOEIC"],"meaningKo":"임시의"},
  {"word":"tend","pos":["v"],"level":["TOEIC"],"meaningKo":"~하는 경향이 있다"},
  {"word":"terminate","pos":["v"],"level":["TOEIC"],"meaningKo":"종료하다"},
  {"word":"thorough","pos":["adj"],"level":["TOEIC"],"meaningKo":"철저한"},
  {"word":"throughout","pos":["prep","adv"],"level":["TOEIC"],"meaningKo":"~내내; 도처에"},
  {"word":"total","pos":["n","adj"],"level":["TOEIC"],"meaningKo":"합계; 총"},
  {"word":"track","pos":["v","n"],"level":["TOEIC"],"meaningKo":"추적하다"},
  {"word":"trade","pos":["n","v"],"level":["TOEIC"],"meaningKo":"무역; 거래하다"},
  {"word":"tradition","pos":["n"],"level":["TOEIC"],"meaningKo":"전통"},
  {"word":"transfer","pos":["v","n"],"level":["TOEIC"],"meaningKo":"이동하다; 이전"},
  {"word":"transform","pos":["v"],"level":["TOEIC"],"meaningKo":"변환하다"},
  {"word":"transport","pos":["n","v"],"level":["TOEIC"],"meaningKo":"운송"},
  {"word":"trend","pos":["n"],"level":["TOEIC"],"meaningKo":"추세; 유행"},
  {"word":"typical","pos":["adj"],"level":["TOEIC"],"meaningKo":"전형적인"},
  {"word":"undergo","pos":["v"],"level":["TOEIC"],"meaningKo":"겪다"},
  {"word":"unique","pos":["adj"],"level":["TOEIC"],"meaningKo":"독특한"},
  {"word":"unless","pos":["conj"],"level":["TOEIC"],"meaningKo":"~하지 않는 한"},
  {"word":"update","pos":["v","n"],"level":["TOEIC"],"meaningKo":"갱신하다"},
  {"word":"upgrade","pos":["v","n"],"level":["TOEIC"],"meaningKo":"업그레이드하다"},
  {"word":"urge","pos":["v"],"level":["TOEIC"],"meaningKo":"촉구하다"},
  {"word":"utilize","pos":["v"],"level":["TOEIC"],"meaningKo":"활용하다"},
  {"word":"valid","pos":["adj"],"level":["TOEIC"],"meaningKo":"유효한"},
  {"word":"value","pos":["n","v"],"level":["TOEIC"],"meaningKo":"가치; 중요시하다"},
  {"word":"various","pos":["adj"],"level":["TOEIC"],"meaningKo":"다양한"},
  {"word":"verify","pos":["v"],"level":["TOEIC"],"meaningKo":"확인하다; 검증하다"},
  {"word":"version","pos":["n"],"level":["TOEIC"],"meaningKo":"버전; 판"},
  {"word":"violate","pos":["v"],"level":["TOEIC"],"meaningKo":"위반하다"},
  {"word":"visible","pos":["adj"],"level":["TOEIC"],"meaningKo":"눈에 보이는"},
  {"word":"volume","pos":["n"],"level":["TOEIC"],"meaningKo":"양; 부피; 권"},
  {"word":"volunteer","pos":["n","v"],"level":["TOEIC"],"meaningKo":"자원봉사자"},
  {"word":"wage","pos":["n"],"level":["TOEIC"],"meaningKo":"임금"},
  {"word":"warn","pos":["v"],"level":["TOEIC"],"meaningKo":"경고하다"},
  {"word":"warranty","pos":["n"],"level":["TOEIC"],"meaningKo":"보증"},
  {"word":"withdraw","pos":["v"],"level":["TOEIC"],"meaningKo":"인출하다; 철수하다"},
  {"word":"workforce","pos":["n"],"level":["TOEIC"],"meaningKo":"인력; 노동력"},
  {"word":"yield","pos":["v","n"],"level":["TOEIC"],"meaningKo":"산출하다; 수익률"}
]
